{
    "key": "group_643de817aba38",
    "title": "CPT Settings",
    "fields": [
        {
            "key": "field_643de81a1a049",
            "label": "Author",
            "name": "author",
            "aria-label": "",
            "type": "text",
            "instructions": "",
            "required": 0,
            "conditional_logic": 0,
            "wrapper": {
                "width": "",
                "class": "",
                "id": ""
            },
            "default_value": "",
            "maxlength": "",
            "placeholder": "",
            "prepend": "",
            "append": ""
        },
        {
            "key": "field_6442c982646d0",
            "label": "Is Talent",
            "name": "is_talent",
            "aria-label": "",
            "type": "true_false",
            "instructions": "",
            "required": 0,
            "conditional_logic": 0,
            "wrapper": {
                "width": "",
                "class": "",
                "id": ""
            },
            "message": "",
            "default_value": 0,
            "ui_on_text": "",
            "ui_off_text": "",
            "ui": 1
        },
        {
            "key": "field_6442c998646d1",
            "label": "Talent",
            "name": "talent",
            "aria-label": "",
            "type": "relationship",
            "instructions": "",
            "required": 0,
            "conditional_logic": [
                [
                    {
                        "field": "field_6442c982646d0",
                        "operator": "==",
                        "value": "1"
                    }
                ]
            ],
            "wrapper": {
                "width": "",
                "class": "",
                "id": ""
            },
            "post_type": [
                "talent"
            ],
            "post_status": "",
            "taxonomy": "",
            "filters": [
                "search"
            ],
            "return_format": "object",
            "min": "",
            "max": "",
            "elements": ""
        },
        {
            "key": "field_6447215b3a8fa",
            "label": "Style",
            "name": "style",
            "aria-label": "",
            "type": "button_group",
            "instructions": "",
            "required": 0,
            "conditional_logic": 0,
            "wrapper": {
                "width": "",
                "class": "",
                "id": ""
            },
            "choices": {
                "red": "Red",
                "blue": "Blue",
                "green": "Green",
                "violet": "Violet"
            },
            "default_value": "",
            "return_format": "value",
            "allow_null": 0,
            "layout": "horizontal"
        }
    ],
    "location": [
        [
            {
                "param": "post_type",
                "operator": "==",
                "value": "post"
            }
        ],
        [
            {
                "param": "post_type",
                "operator": "==",
                "value": "project"
            }
        ]
    ],
    "menu_order": 0,
    "position": "normal",
    "style": "default",
    "label_placement": "top",
    "instruction_placement": "label",
    "hide_on_screen": "",
    "active": true,
    "description": "",
    "show_in_rest": 0,
    "modified": 1682383234
}